source_atlas/__init__.py
source_atlas/__main__.py
source_atlas/cli.py
source_atlas/py.typed
source_atlas/analyzers/analyzer_factory.py
source_atlas/analyzers/base_analyzer.py
source_atlas/analyzers/java_analyzer.py
source_atlas/config/config.py
source_atlas/config/java_constants.py
source_atlas/extractors/base_extractor.py
source_atlas/extractors/java/java_extractor.py
source_atlas/extractors/java/kafka_extractor.py
source_atlas/extractors/java/quarkus_extractor.py
source_atlas/extractors/java/rabbit_extractor.py
source_atlas/extractors/java/spring_event_extractor.py
source_atlas/extractors/java/springboot_annotation_extractor.py
source_atlas/lsp/lsp_service.py
source_atlas/lsp/multilspy/__init__.py
source_atlas/lsp/multilspy/language_server.py
source_atlas/lsp/multilspy/multilspy_config.py
source_atlas/lsp/multilspy/multilspy_exceptions.py
source_atlas/lsp/multilspy/multilspy_logger.py
source_atlas/lsp/multilspy/multilspy_settings.py
source_atlas/lsp/multilspy/multilspy_types.py
source_atlas/lsp/multilspy/multilspy_utils.py
source_atlas/lsp/multilspy/type_helpers.py
source_atlas/lsp/multilspy/language_servers/clangd_language_server/clangd_language_server.py
source_atlas/lsp/multilspy/language_servers/clangd_language_server/initialize_params.json
source_atlas/lsp/multilspy/language_servers/clangd_language_server/runtime_dependencies.json
source_atlas/lsp/multilspy/language_servers/dart_language_server/dart_language_server.py
source_atlas/lsp/multilspy/language_servers/dart_language_server/initialize_params.json
source_atlas/lsp/multilspy/language_servers/dart_language_server/runtime_dependencies.json
source_atlas/lsp/multilspy/language_servers/eclipse_jdtls/eclipse_jdtls.py
source_atlas/lsp/multilspy/language_servers/eclipse_jdtls/initialize_params.json
source_atlas/lsp/multilspy/language_servers/eclipse_jdtls/runtime_dependencies.json
source_atlas/lsp/multilspy/language_servers/eclipse_jdtls/static/gradle-7.3.3/init.d/readme.txt
source_atlas-0.1.9.dist-info/licenses/LICENSE
source_atlas-0.1.9.dist-info/METADATA
source_atlas-0.1.9.dist-info/WHEEL
source_atlas-0.1.9.dist-info/entry_points.txt
source_atlas-0.1.9.dist-info/top_level.txt
source_atlas-0.1.9.dist-info/RECORD
