Metadata-Version: 2.4
Name: source-atlas
Version: 0.1.9
Summary: Multi-language code analyzer with LSP and Neo4j integration
Author-email: Nguyen Van Quyen <quyennv.4work@gmail.com>
License: MIT
Project-URL: Homepage, https://github.com/quyen-ngv/source-atlas
Project-URL: Documentation, https://github.com/quyen-ngv/source-atlas#readme
Project-URL: Repository, https://github.com/quyen-ngv/source-atlas
Project-URL: Issues, https://github.com/quyen-ngv/source-atlas/issues
Project-URL: Changelog, https://github.com/quyen-ngv/source-atlas/blob/main/CHANGELOG.md
Keywords: code-analysis,ast,lsp,neo4j,graph,static-analysis
Classifier: Development Status :: 3 - Alpha
Classifier: Intended Audience :: Developers
Classifier: License :: OSI Approved :: MIT License
Classifier: Operating System :: OS Independent
Classifier: Programming Language :: Python :: 3
Classifier: Programming Language :: Python :: 3.8
Classifier: Programming Language :: Python :: 3.9
Classifier: Programming Language :: Python :: 3.10
Classifier: Programming Language :: Python :: 3.11
Classifier: Programming Language :: Python :: 3.12
Classifier: Topic :: Software Development :: Code Generators
Classifier: Topic :: Software Development :: Libraries :: Python Modules
Classifier: Topic :: Software Development :: Quality Assurance
Requires-Python: >=3.8
License-File: LICENSE
Requires-Dist: loguru<0.8.0,>=0.7.3
Requires-Dist: python-dotenv<2.0.0,>=1.1.1
Requires-Dist: cryptography<43,>=41.0.0
Requires-Dist: tree-sitter==0.25.1
Requires-Dist: tree-sitter-language-pack==0.9.0
Requires-Dist: jedi-language-server==0.41.1
Requires-Dist: setuptools
Requires-Dist: psutil<8.0.0,>=7.0.0
Requires-Dist: requests==2.32.3
Requires-Dist: neo4j==5.14.0
Requires-Dist: pydantic-settings<3.0.0,>=2.11.0
Provides-Extra: dev
Requires-Dist: pytest>=7.0.0; extra == "dev"
Requires-Dist: pytest-cov>=4.0.0; extra == "dev"
Requires-Dist: black>=23.0.0; extra == "dev"
Requires-Dist: flake8>=6.0.0; extra == "dev"
Requires-Dist: mypy>=1.0.0; extra == "dev"
Requires-Dist: pre-commit>=3.0.0; extra == "dev"
Requires-Dist: sphinx>=5.0.0; extra == "dev"
Requires-Dist: sphinx-rtd-theme>=1.0.0; extra == "dev"
Dynamic: license-file
